restcountries/__init__.py
restcountries/api.py
restcountries/client.py
restcountries/country.py
restcountries/expections.py
restcountries/models.py
restcountries-1.1.3.dist-info/LICENSE
restcountries-1.1.3.dist-info/METADATA
restcountries-1.1.3.dist-info/WHEEL
restcountries-1.1.3.dist-info/top_level.txt
restcountries-1.1.3.dist-info/zip-safe
restcountries-1.1.3.dist-info/RECORD
