Metadata-Version: 1.1
Name: restcountries
Version: 1.1.3
Summary: A Python client for the RestCountries API.
Home-page: http://github.com/yakupadakli/restcountries.git
Author: Yakup Adaklı
Author-email: yakup.adakli@gmail.com
License: MIT
Keywords: restcountries library countries
Platform: UNKNOWN
Classifier: Development Status :: 5 - Production/Stable
Classifier: Topic :: Software Development :: Libraries
Classifier: License :: OSI Approved :: MIT License
Classifier: Operating System :: OS Independent
Classifier: Programming Language :: Python :: 2.7
Classifier: Programming Language :: Python :: 3.4
Classifier: Programming Language :: Python :: 3.5
Classifier: Programming Language :: Python :: 3.6
